pyscada/__init__.py
pyscada/serial/__init__.py
pyscada/serial/admin.py
pyscada/serial/apps.py
pyscada/serial/device.py
pyscada/serial/models.py
pyscada/serial/signals.py
pyscada/serial/worker.py
pyscada/serial/devices/AirLinkGX450.py
pyscada/serial/devices/__init__.py
pyscada/serial/migrations/0001_initial.py
pyscada/serial/migrations/0002_add_device_protocol.py
pyscada/serial/migrations/0003_auto_20200903_1507.py
pyscada/serial/migrations/0004_auto_20200903_1513.py
pyscada/serial/migrations/0005_serialdevice_instrument.py
pyscada/serial/migrations/0006_auto_20200904_0824.py
pyscada/serial/migrations/0007_auto_20200904_0832.py
pyscada/serial/migrations/0008_auto_20200904_0837.py
pyscada/serial/migrations/0009_serialdevice_instrument_handler.py
pyscada/serial/migrations/0010_devicehandler_migration.py
pyscada/serial/migrations/0011_remove_serialdevice_instrument.py
pyscada/serial/migrations/0012_auto_20210601_1244.py
pyscada/serial/migrations/0013_devicehandler_migration.py
pyscada/serial/migrations/0014_remove_serialdevice_instrument_handler.py
pyscada/serial/migrations/__init__.py
pyscada_serial-0.8.0.dist-info/AUTHORS
pyscada_serial-0.8.0.dist-info/LICENSE
pyscada_serial-0.8.0.dist-info/METADATA
pyscada_serial-0.8.0.dist-info/WHEEL
pyscada_serial-0.8.0.dist-info/top_level.txt
pyscada_serial-0.8.0.dist-info/RECORD
